{"nodes": [{"id": "d_dev_profile_kanitmann_docs_agents_issue_tracker_md", "label": "issue-tracker.md", "file_type": "document", "source_file": "docs/agents/issue-tracker.md", "source_location": "L1"}, {"id": "agents_issue_tracker_issue_tracker", "label": "Issue tracker", "file_type": "document", "source_file": "docs/agents/issue-tracker.md", "source_location": "L1"}, {"id": "agents_issue_tracker_create", "label": "Create", "file_type": "document", "source_file": "docs/agents/issue-tracker.md", "source_location": "L6"}, {"id": "agents_issue_tracker_list", "label": "List", "file_type": "document", "source_file": "docs/agents/issue-tracker.md", "source_location": "L14"}, {"id": "agents_issue_tracker_search", "label": "Search", "file_type": "document", "source_file": "docs/agents/issue-tracker.md", "source_location": "L25"}, {"id": "agents_issue_tracker_view", "label": "View", "file_type": "document", "source_file": "docs/agents/issue-tracker.md", "source_location": "L33"}, {"id": "agents_issue_tracker_update_edit", "label": "Update / Edit", "file_type": "document", "source_file": "docs/agents/issue-tracker.md", "source_location": "L41"}, {"id": "agents_issue_tracker_close_reopen", "label": "Close / Reopen", "file_type": "document", "source_file": "docs/agents/issue-tracker.md", "source_location": "L48"}, {"id": "agents_issue_tracker_comment", "label": "Comment", "file_type": "document", "source_file": "docs/agents/issue-tracker.md", "source_location": "L56"}, {"id": "agents_issue_tracker_labels", "label": "Labels", "file_type": "document", "source_file": "docs/agents/issue-tracker.md", "source_location": "L62"}, {"id": "agents_issue_tracker_assign", "label": "Assign", "file_type": "document", "source_file": "docs/agents/issue-tracker.md", "source_location": "L70"}, {"id": "agents_issue_tracker_link_prs_to_issues", "label": "Link PRs to issues", "file_type": "document", "source_file": "docs/agents/issue-tracker.md", "source_location": "L78"}, {"id": "agents_issue_tracker_notes", "label": "Notes", "file_type": "document", "source_file": "docs/agents/issue-tracker.md", "source_location": "L82"}], "edges": [{"source": "d_dev_profile_kanitmann_docs_agents_issue_tracker_md", "target": "agents_issue_tracker_issue_tracker", "relation": "contains", "confidence": "EXTRACTED", "source_file": "docs/agents/issue-tracker.md", "source_location": "L1", "weight": 1.0}, {"source": "agents_issue_tracker_issue_tracker", "target": "agents_issue_tracker_create", "relation": "contains", "confidence": "EXTRACTED", "source_file": "docs/agents/issue-tracker.md", "source_location": "L6", "weight": 1.0}, {"source": "agents_issue_tracker_issue_tracker", "target": "agents_issue_tracker_list", "relation": "contains", "confidence": "EXTRACTED", "source_file": "docs/agents/issue-tracker.md", "source_location": "L14", "weight": 1.0}, {"source": "agents_issue_tracker_issue_tracker", "target": "agents_issue_tracker_search", "relation": "contains", "confidence": "EXTRACTED", "source_file": "docs/agents/issue-tracker.md", "source_location": "L25", "weight": 1.0}, {"source": "agents_issue_tracker_issue_tracker", "target": "agents_issue_tracker_view", "relation": "contains", "confidence": "EXTRACTED", "source_file": "docs/agents/issue-tracker.md", "source_location": "L33", "weight": 1.0}, {"source": "agents_issue_tracker_issue_tracker", "target": "agents_issue_tracker_update_edit", "relation": "contains", "confidence": "EXTRACTED", "source_file": "docs/agents/issue-tracker.md", "source_location": "L41", "weight": 1.0}, {"source": "agents_issue_tracker_issue_tracker", "target": "agents_issue_tracker_close_reopen", "relation": "contains", "confidence": "EXTRACTED", "source_file": "docs/agents/issue-tracker.md", "source_location": "L48", "weight": 1.0}, {"source": "agents_issue_tracker_issue_tracker", "target": "agents_issue_tracker_comment", "relation": "contains", "confidence": "EXTRACTED", "source_file": "docs/agents/issue-tracker.md", "source_location": "L56", "weight": 1.0}, {"source": "agents_issue_tracker_issue_tracker", "target": "agents_issue_tracker_labels", "relation": "contains", "confidence": "EXTRACTED", "source_file": "docs/agents/issue-tracker.md", "source_location": "L62", "weight": 1.0}, {"source": "agents_issue_tracker_issue_tracker", "target": "agents_issue_tracker_assign", "relation": "contains", "confidence": "EXTRACTED", "source_file": "docs/agents/issue-tracker.md", "source_location": "L70", "weight": 1.0}, {"source": "agents_issue_tracker_issue_tracker", "target": "agents_issue_tracker_link_prs_to_issues", "relation": "contains", "confidence": "EXTRACTED", "source_file": "docs/agents/issue-tracker.md", "source_location": "L78", "weight": 1.0}, {"source": "agents_issue_tracker_issue_tracker", "target": "agents_issue_tracker_notes", "relation": "contains", "confidence": "EXTRACTED", "source_file": "docs/agents/issue-tracker.md", "source_location": "L82", "weight": 1.0}], "input_tokens": 0, "output_tokens": 0}